volttronwrapper/__init__.py
volttronwrapper/main.py
volttron-11.0.0rc3.dist-info/METADATA
volttron-11.0.0rc3.dist-info/WHEEL
volttron-11.0.0rc3.dist-info/RECORD
